beta_rec/__init__.py
beta_rec/core/__init__.py
beta_rec/core/config.py
beta_rec/core/eval_engine.py
beta_rec/core/recommender.py
beta_rec/core/train_engine.py
beta_rec/data/__init__.py
beta_rec/data/auxiliary_data.py
beta_rec/data/base_data.py
beta_rec/data/data_loaders.py
beta_rec/data/deprecated_data.py
beta_rec/data/deprecated_data_base.py
beta_rec/data/grocery_data.py
beta_rec/data/sequential_data.py
beta_rec/datasets/__init__.py
beta_rec/datasets/ali_mobile.py
beta_rec/datasets/amazon.py
beta_rec/datasets/citeulike.py
beta_rec/datasets/data_load.py
beta_rec/datasets/data_split.py
beta_rec/datasets/dataset_base.py
beta_rec/datasets/diginetica.py
beta_rec/datasets/dunnhumby.py
beta_rec/datasets/epinions.py
beta_rec/datasets/gowalla.py
beta_rec/datasets/hetrec.py
beta_rec/datasets/instacart.py
beta_rec/datasets/last_fm.py
beta_rec/datasets/movielens.py
beta_rec/datasets/retailrocket.py
beta_rec/datasets/seq_data_utils.py
beta_rec/datasets/tafeng.py
beta_rec/datasets/taobao.py
beta_rec/datasets/yelp.py
beta_rec/datasets/yoochoose.py
beta_rec/models/__init__.py
beta_rec/models/cmn.py
beta_rec/models/gmf.py
beta_rec/models/lcfn.py
beta_rec/models/lightgcn.py
beta_rec/models/mf.py
beta_rec/models/mlp.py
beta_rec/models/narm.py
beta_rec/models/ncf.py
beta_rec/models/ngcf.py
beta_rec/models/pairwise_gmf.py
beta_rec/models/sasrec.py
beta_rec/models/tisasrec.py
beta_rec/models/torch_engine.py
beta_rec/models/triple2vec.py
beta_rec/models/vbcar.py
beta_rec/models/vlml.py
beta_rec/recommenders/__init__.py
beta_rec/recommenders/lightgcn.py
beta_rec/recommenders/matrix_factorization.py
beta_rec/recommenders/narm.py
beta_rec/recommenders/ncf.py
beta_rec/recommenders/ngcf.py
beta_rec/recommenders/sasrec.py
beta_rec/recommenders/tisasrec.py
beta_rec/recommenders/triple2vec.py
beta_rec/recommenders/vbcar.py
beta_rec/utils/__init__.py
beta_rec/utils/alias_table.py
beta_rec/utils/common_util.py
beta_rec/utils/constants.py
beta_rec/utils/download.py
beta_rec/utils/evaluation.py
beta_rec-0.3.2.dist-info/LICENSE
beta_rec-0.3.2.dist-info/METADATA
beta_rec-0.3.2.dist-info/WHEEL
beta_rec-0.3.2.dist-info/top_level.txt
beta_rec-0.3.2.dist-info/RECORD
