Metadata-Version: 2.1
Name: beta-rec
Version: 0.3.2
Summary: Beta-RecSys: Build, Evaluate and Tune Automated Recommender Systems
Home-page: https://github.com/beta-team/beta-recsys
Author-email: recsys.beta@gmail.com
License: UNKNOWN
Download-URL: https://github.com/beta-team/beta-recsys/archive/0.3.2.tar.gz
Keywords: pytorch,recommender system,recommendations
Platform: UNKNOWN
Requires-Python: >=3.6.9
Requires-Dist: requests (==2.24.0)
Requires-Dist: tensorboardX (>=2.1)
Requires-Dist: ray (==1.0.1)
Requires-Dist: torch (>=1.7.1)
Requires-Dist: numpy (>=1.16.0)
Requires-Dist: tqdm (>=4.45.0)
Requires-Dist: pandas (==1.0.3)
Requires-Dist: mock (==4.0.1)
Requires-Dist: scipy (>=1.4)
Requires-Dist: scikit-learn (>=0.22)
Requires-Dist: gputil (==1.4.0)
Requires-Dist: aiofiles (~=0.4.0)
Requires-Dist: aiohttp (>=3.7.4)
Requires-Dist: nest-asyncio (~=1.3.3)
Requires-Dist: py-cpuinfo (~=5.0.0)
Requires-Dist: psutil (~=5.7.0)
Requires-Dist: tabulate (~=0.8.7)
Requires-Dist: py7zr (~=0.6)
Requires-Dist: rstcheck (~=3.3.1)
Requires-Dist: munch (==2.5.0)
